Metadata-Version: 2.1
Name: scope-plot
Version: 0.2.4
Summary: Plot Google Benchmark results
Home-page: https://github.com/rai-project/scope_plot
Author: Abdul Dakkak
Author-email: dakkak@illinois.edu
Maintainer: Carl Pearson
Maintainer-email: pearson@illinois.edu
License: Apache 2.0
Keywords: scope_plot
Platform: UNKNOWN
Classifier: Intended Audience :: Developers
Classifier: License :: OSI Approved :: MIT License
Classifier: Natural Language :: English
Classifier: Operating System :: OS Independent
Classifier: Programming Language :: Python :: 2
Classifier: Programming Language :: Python :: 2.7
Classifier: Programming Language :: Python :: 3
Classifier: Programming Language :: Python :: 3.5
Classifier: Programming Language :: Python :: 3.6
Classifier: Programming Language :: Python :: 3.7
